{
  "$schema": "https://ui.shadcn.com/schema/registry-item.json",
  "name": "instagram-post",
  "title": "Instagram Post",
  "author": "mcpcn",
  "description": "Instagram post card with image and engagement.",
  "dependencies": [
    "@base-ui/react",
    "lucide-react"
  ],
  "registryDependencies": [
    "dropdown-menu"
  ],
  "files": [
    {
      "path": "registry/social/instagram-post.tsx",
      "content": "\"use client\";\n\nimport {\n  Bookmark,\n  Code,\n  Flag,\n  Heart,\n  Link,\n  MessageCircle,\n  MoreHorizontal,\n  Send,\n  UserMinus,\n} from \"lucide-react\";\nimport { createContext, createElement, useContext } from \"react\";\nimport type { ComponentProps, ImgHTMLAttributes } from \"react\";\n\nimport {\n  DropdownMenu,\n  DropdownMenuContent,\n  DropdownMenuItem,\n  DropdownMenuSeparator,\n  DropdownMenuTrigger,\n} from \"@/components/ui/dropdown-menu\";\nimport { cn } from \"@/lib/utils\";\n\nconst BlockImage = (props: ImgHTMLAttributes<HTMLImageElement>) =>\n  createElement(\"img\", props);\n\ninterface InstagramPostData {\n  author?: string;\n  avatar?: string;\n  caption?: string;\n  image?: string;\n  likes?: string;\n  time?: string;\n  verified?: boolean;\n}\n\nconst DEFAULT_POST: InstagramPostData = {\n  author: \"mcpcn\",\n  avatar: \"M\",\n  caption: \"Building the future of agentic UIs, one component at a time.\",\n  image: \"https://images.unsplash.com/photo-1506905925346-21bda4d32df4?w=800\",\n  likes: \"2,847\",\n  time: \"2h\",\n  verified: true,\n};\n\nconst InstagramPostContext = createContext<InstagramPostData | null>(null);\n\nexport const useInstagramPost = () => {\n  const context = useContext(InstagramPostContext);\n  if (!context) {\n    throw new Error(\n      \"InstagramPost components must be used within InstagramPost\"\n    );\n  }\n  return context;\n};\n\nexport interface InstagramPostProps extends ComponentProps<\"article\"> {\n  data?: InstagramPostData;\n}\n\nconst InstagramPostMenu = () => (\n  <DropdownMenu>\n    <DropdownMenuTrigger asChild>\n      <button\n        className=\"cursor-pointer text-foreground transition-colors hover:text-muted-foreground\"\n        type=\"button\"\n      >\n        <MoreHorizontal className=\"size-5\" />\n      </button>\n    </DropdownMenuTrigger>\n    <DropdownMenuContent align=\"end\">\n      <DropdownMenuItem>\n        <Flag className=\"mr-2 size-4\" />\n        Report\n      </DropdownMenuItem>\n      <DropdownMenuItem>\n        <UserMinus className=\"mr-2 size-4\" />\n        Unfollow\n      </DropdownMenuItem>\n      <DropdownMenuSeparator />\n      <DropdownMenuItem>\n        <Link className=\"mr-2 size-4\" />\n        Copy link\n      </DropdownMenuItem>\n      <DropdownMenuItem>\n        <Code className=\"mr-2 size-4\" />\n        Embed\n      </DropdownMenuItem>\n    </DropdownMenuContent>\n  </DropdownMenu>\n);\n\nexport const InstagramPostHeader = ({\n  children,\n  className,\n  ...props\n}: ComponentProps<\"div\">) => {\n  const data = useInstagramPost();\n  return (\n    <div\n      className={cn(\"flex items-center justify-between p-3\", className)}\n      {...props}\n    >\n      {children ?? (\n        <>\n          <div className=\"flex items-center gap-2\">\n            {data.avatar && (\n              <div className=\"size-8 rounded-full bg-gradient-to-br from-[#833AB4] via-[#FD1D1D] to-[#F77737] p-0.5\">\n                <div className=\"flex size-full items-center justify-center rounded-full bg-card font-semibold text-xs\">\n                  {data.avatar}\n                </div>\n              </div>\n            )}\n            <div className=\"flex items-center gap-1\">\n              {data.author && (\n                <span className=\"font-semibold text-sm\">{data.author}</span>\n              )}\n              {data.verified && (\n                <span className=\"flex size-3.5 items-center justify-center rounded-full bg-blue-500 text-[9px] text-white\">\n                  ✓\n                </span>\n              )}\n            </div>\n          </div>\n          <InstagramPostMenu />\n        </>\n      )}\n    </div>\n  );\n};\n\nexport const InstagramPostMedia = ({\n  className,\n  ...props\n}: ComponentProps<\"div\">) => {\n  const data = useInstagramPost();\n  if (!data.image) {\n    return null;\n  }\n  return (\n    <div className={cn(\"aspect-square bg-muted\", className)} {...props}>\n      <BlockImage\n        alt={\n          data.author ? `Instagram post by ${data.author}` : \"Instagram post\"\n        }\n        className=\"size-full object-cover\"\n        src={data.image}\n      />\n    </div>\n  );\n};\n\nexport const InstagramPostActions = ({\n  children,\n  className,\n  ...props\n}: ComponentProps<\"div\">) => (\n  <div\n    className={cn(\"flex items-center justify-between\", className)}\n    {...props}\n  >\n    {children ?? (\n      <>\n        <div className=\"flex items-center gap-4\">\n          <button\n            aria-label=\"Like\"\n            className=\"cursor-pointer transition-colors hover:text-muted-foreground\"\n            type=\"button\"\n          >\n            <Heart className=\"size-6\" />\n          </button>\n          <button\n            aria-label=\"Comment\"\n            className=\"cursor-pointer transition-colors hover:text-muted-foreground\"\n            type=\"button\"\n          >\n            <MessageCircle className=\"size-6\" />\n          </button>\n          <button\n            aria-label=\"Share\"\n            className=\"cursor-pointer transition-colors hover:text-muted-foreground\"\n            type=\"button\"\n          >\n            <Send className=\"size-6\" />\n          </button>\n        </div>\n        <button\n          aria-label=\"Save\"\n          className=\"cursor-pointer transition-colors hover:text-muted-foreground\"\n          type=\"button\"\n        >\n          <Bookmark className=\"size-6\" />\n        </button>\n      </>\n    )}\n  </div>\n);\n\nexport const InstagramPostContent = ({\n  children,\n  className,\n  ...props\n}: ComponentProps<\"div\">) => {\n  const data = useInstagramPost();\n  return (\n    <div className={cn(\"space-y-2 p-3\", className)} {...props}>\n      {children ?? (\n        <>\n          <InstagramPostActions />\n          {data.likes && (\n            <p className=\"font-semibold text-sm\">{data.likes} likes</p>\n          )}\n          {(data.author || data.caption) && (\n            <p className=\"text-sm\">\n              {data.author && (\n                <span className=\"font-semibold\">{data.author}</span>\n              )}\n              {data.author && data.caption && \" \"}\n              {data.caption}\n            </p>\n          )}\n          {data.time && (\n            <p className=\"text-muted-foreground text-xs\">{data.time}</p>\n          )}\n        </>\n      )}\n    </div>\n  );\n};\n\nconst InstagramPostRoot = ({\n  children,\n  className,\n  data,\n  ...props\n}: InstagramPostProps) => {\n  const value = data ?? DEFAULT_POST;\n  return (\n    <InstagramPostContext.Provider value={value}>\n      <article\n        className={cn(\"overflow-hidden rounded-xl border bg-card\", className)}\n        {...props}\n      >\n        {children ?? (\n          <>\n            <InstagramPostHeader />\n            <InstagramPostMedia />\n            <InstagramPostContent />\n          </>\n        )}\n      </article>\n    </InstagramPostContext.Provider>\n  );\n};\n\nexport const InstagramPost = InstagramPostRoot;\n",
      "type": "registry:block",
      "target": "components/ui/instagram-post.tsx"
    }
  ],
  "meta": {
    "preview": "https://mcpcn.dev/previews/instagram-post.png",
    "version": "1.2.0",
    "changelog": {
      "1.0.0": "Initial release with image and engagement display",
      "1.0.1": "Improved alt text to include author name",
      "1.0.3": "Added comprehensive JSDoc documentation",
      "1.1.0": "Moved to social category for better organization",
      "1.1.1": "Updated Props interface with decorative header and sub-parameter JSDoc documentation",
      "1.1.2": "Removed default content data - component only renders explicitly provided data",
      "1.1.3": "Added aria-labels to icon-only action buttons for accessibility",
      "1.2.0": "Added demo data defaults - component renders demo content when no data prop is provided"
    }
  },
  "categories": [
    "social"
  ],
  "type": "registry:block"
}